ourl.py
setup.py
ourl.egg-info/PKG-INFO
ourl.egg-info/SOURCES.txt
ourl.egg-info/dependency_links.txt
ourl.egg-info/entry_points.txt
ourl.egg-info/requires.txt
ourl.egg-info/top_level.txt